writer/__init__.py
writer/ai_content_detector.py
writer/billing.py
writer/completions.py
writer/content.py
writer/cowrite.py
writer/download_the_customized_model.py
writer/files.py
writer/fine_tunes.py
writer/models.py
writer/sdk.py
writer/snippet.py
writer/styleguide.py
writer/terminology.py
writer/user.py
writer/models/__init__.py
writer/models/operations/__init__.py
writer/models/operations/addterms.py
writer/models/operations/completions.py
writer/models/operations/contentcheck.py
writer/models/operations/contentdetectorapi.py
writer/models/operations/contetncorrect.py
writer/models/operations/createmodelcustomization.py
writer/models/operations/customizationcompletions.py
writer/models/operations/customizations.py
writer/models/operations/deletefile.py
writer/models/operations/deletemodelcustomization.py
writer/models/operations/deletesnippets.py
writer/models/operations/deleteterms.py
writer/models/operations/fetchcustomizedmodelfile.py
writer/models/operations/files.py
writer/models/operations/findsnippets.py
writer/models/operations/findterms.py
writer/models/operations/generate_content.py
writer/models/operations/get_subscription_details.py
writer/models/operations/get_template_inputs.py
writer/models/operations/getfile.py
writer/models/operations/getmodelcustomization.py
writer/models/operations/listpages.py
writer/models/operations/listusers.py
writer/models/operations/models.py
writer/models/operations/pagedetails.py
writer/models/operations/updatesnippets.py
writer/models/operations/updateterms.py
writer/models/operations/uploadfile.py
writer/models/shared/__init__.py
writer/models/shared/approvedtermextension.py
writer/models/shared/approvedtermextensioncreate.py
writer/models/shared/completiongenerationchoice.py
writer/models/shared/completiongenerationchoicelogprobs.py
writer/models/shared/completionrequest.py
writer/models/shared/completionresponse.py
writer/models/shared/contentdetectorrequest.py
writer/models/shared/contentdetectorresponse.py
writerai_api-0.2.0.dist-info/METADATA
writerai_api-0.2.0.dist-info/WHEEL
writerai_api-0.2.0.dist-info/top_level.txt
writerai_api-0.2.0.dist-info/RECORD
